.gitignore
LICENSE.txt
Makefile
README.rst
README.txt
TODO.txt
deps.txt
setup.py
test.py
benchbase/__init__.py
benchbase/bencher.py
benchbase/command.py
benchbase/funkload.py
benchbase/jmeter.py
benchbase/main.py
benchbase/model.py
benchbase/report.py
benchbase/sar.py
benchbase/sqlitext.py
benchbase/util.py
benchbase.egg-info/PKG-INFO
benchbase.egg-info/SOURCES.txt
benchbase.egg-info/dependency_links.txt
benchbase.egg-info/entry_points.txt
benchbase.egg-info/requires.txt
benchbase.egg-info/top_level.txt
benchbase.egg-info/zip-safe
benchbase/templates/benchbase.css
benchbase/templates/report.mako
benchbase/templates/sample-gplot.mako
benchbase/templates/sar-gplot.mako
tests/bench-fl/funkload.xml.gz
tests/bench-jm-csv/gc.log.gz
tests/bench-jm-csv/jmeter.csv.gz
tests/bench-jm-csv/sysstat-sar.log.gz
tests/bench-jm-xml/gc.log.gz
tests/bench-jm-xml/jmeter.xml.gz
tests/bench-jm-xml/jmxstat.log.gz
tests/bench-jm-xml/sysstat-sar.log.gz