Metadata-Version: 1.0
Name: benchbase
Version: 1.1.0
Summary: Store bench result from JMeter of FunkLoad for reporting.
Home-page: http://pypi.python.org/pypi/benchbase
Author: Benoit Delbosc
Author-email: bdelbosc@nuxeo.com
License: GPL
Download-URL: http://pypi.python.org/packages/source/t/benchbase/benchbase-1.1.0.tar.gz
Keywords: benchmark jmeter funkload report chart
Platform: UNKNOWN
Classifier: Development Status :: 4 - Beta
Classifier: Environment :: Console
Classifier: Intended Audience :: Developers
Classifier: Intended Audience :: Information Technology
Classifier: Intended Audience :: System Administrators
Classifier: Natural Language :: English
Classifier: License :: OSI Approved :: GNU General Public License (GPL)
Classifier: Operating System :: OS Independent
Classifier: Programming Language :: Python
Classifier: Topic :: Software Development :: Quality Assurance
